classclick/__init__.py
classclick/args.py
classclick/cli.py
classclick/command.py
classclick/helpers.py
classclick-0.0.1.dist-info/LICENSE
classclick-0.0.1.dist-info/METADATA
classclick-0.0.1.dist-info/WHEEL
classclick-0.0.1.dist-info/top_level.txt
classclick-0.0.1.dist-info/RECORD
