Metadata-Version: 2.1
Name: classclick
Version: 0.0.1
Summary: Class Wrapper for Click
Author: Ernest Feret
License-File: LICENSE
Requires-Dist: Click
Requires-Dist: pytest
